{
  "metadata": {
    "title": "Shaft Design Problem",
    "subject": "Mechanics of Solids",
    "documentType": "problem-set"
  },
  "pages": [
    {
      "pageIndex": 0,
      "content": [
        {
          "type": "paragraph",
          "text": "Q A shaft supported by pair of bearing with centre to centre which carries pulley at centre of weight $1 KN$. find the diameter of the shaft. If the allowable bending stress is $40 MPa$?"
        },
        {
          "type": "paragraph",
          "text": "Solution:"
        },
        {
          "type": "math",
          "latex": "\\sigma_{max} = 40 MPa = 40 \\times 10^6 N/m^2 = 40 N/mm^2",
          "display": true
        },
        {
          "type": "math",
          "latex": "P = 1000 N",
          "display": true
        },
        {
          "type": "diagram",
          "description": "A simply supported beam (shaft) with supports at A and C. A point load of 1000 N is applied at the center, point B. Reactions R_A and R_B (labeled R_C) are shown at supports A and C. The distance between supports is 1.0 m or 1000 mm. The load is at 0.5m from A and C.",
          "label": "Beam Diagram"
        },
        {
          "type": "math",
          "latex": "M_{max} = \\frac{\\pi}{32} d^3",
          "display": true
        },
        {
          "type": "math",
          "latex": "R_A + R_B = 1000 N",
          "display": true
        },
        {
          "type": "paragraph",
          "text": "BM at A."
        },
        {
          "type": "math",
          "latex": "M_A = 0",
          "display": true
        },
        {
          "type": "paragraph",
          "text": "BM at B."
        },
        {
          "type": "math",
          "latex": "R_B = 1000 \\times 0.5",
          "display": true
        },
        {
          "type": "math",
          "latex": "R_B = 500 N",
          "display": true
        },
        {
          "type": "math",
          "latex": "R_A = 500 N",
          "display": true
        },
        {
          "type": "math",
          "latex": "M_B = 500 \\times 0.5 = 250 Nm",
          "display": true
        },
        {
          "type": "math",
          "latex": "= 250 \\times 10^3 Nmm",
          "display": true
        },
        {
          "type": "paragraph",
          "text": "BM at C."
        },
        {
          "type": "math",
          "latex": "M_C = 500 \\times 1 = 500 Nm",
          "display": true
        },
        {
          "type": "math",
          "latex": " = (250 \\times 10^3) N mm",
          "display": true
        }
      ]
    }
  ]
}